{
  "schemaVersion": 1,
  "webglContentHash": "c85ec284f1d07c8573c2829400b87c076db3e285d169a7ab4e26bcafccc25b0f",
  "attestedAt": "2026-06-14T23:36:19.574Z",
  "attestedBy": "tmayshark@gmail.com",
  "gitHeadAtAttest": "036b1f29fe7f92d8a8d85fc8986b66805b1489ed",
  "playwrightVersion": "1.50.0",
  "os": "darwin 25.4.0 (arm64)",
  "host": "2600hzs-MacBook-Pro.local",
  "gpu": "ANGLE (Apple, ANGLE Metal Renderer: Apple M5, Unspecified Version)",
  "repeatEach": 1,
  "suites": {
    "A-heavy": {
      "specFiles": 42,
      "passed": 166,
      "failed": 0,
      "flaky": 1,
      "skipped": 0
    },
    "B-leakers": {
      "specFiles": 5,
      "passed": 13,
      "failed": 0,
      "flaky": 0,
      "skipped": 0
    },
    "C-camera": {
      "specFiles": 1,
      "passed": 2,
      "failed": 0,
      "flaky": 0,
      "skipped": 0
    }
  },
  "durationSec": 286
}
